LICENSE
MANIFEST.in
README.md
setup.py
goosepaper/__init__.py
goosepaper/__main__.py
goosepaper/auth.py
goosepaper/goosepaper.py
goosepaper/multiparser.py
goosepaper/story.py
goosepaper/styles.py
goosepaper/test_goosepaper.py
goosepaper/test_utils.py
goosepaper/upload.py
goosepaper/util.py
goosepaper.egg-info/PKG-INFO
goosepaper.egg-info/SOURCES.txt
goosepaper.egg-info/dependency_links.txt
goosepaper.egg-info/entry_points.txt
goosepaper.egg-info/requires.txt
goosepaper.egg-info/top_level.txt
goosepaper/storyprovider/__init__.py
goosepaper/storyprovider/mastodon.py
goosepaper/storyprovider/reddit.py
goosepaper/storyprovider/rss.py
goosepaper/storyprovider/storyprovider.py
goosepaper/storyprovider/test_mastodon.py
goosepaper/storyprovider/weather.py
goosepaper/storyprovider/wikipedia.py
styles/Academy/stylesheet.css
styles/Autumn/stylesheet.css
styles/Autumn/stylesheets.txt
styles/FifthAvenue/stylesheet.css
styles/FifthAvenue/stylesheets.txt