Metadata-Version: 2.1
Name: goosepaper
Version: 0.7.0
Summary: Generate and deliver a daily newspaper PDF
Download-URL: https://github.com/j6k4m8/goosepaper/tarball/0.7.0
Author: Jordan Matelsky
Author-email: opensource@matelsky.com
License: Apache 2.0
Keywords: remarkable,tablet,pdf,news
Classifier: Development Status :: 4 - Beta
Classifier: Intended Audience :: Developers
Classifier: Programming Language :: Python :: 3.7
Classifier: Programming Language :: Python :: 3.8
Classifier: Programming Language :: Python :: 3.9
License-File: LICENSE
